{
  "140": {
    "id": 140,
    "title": "TBD",
    "description": "TBD"
  },
  "139": {
    "id": 139,
    "title": "Keynote",
    "description": "",
    "speakers": [
      "bok"
    ],
    "tags": [
      "General"
    ]    
  },
  "138": {
    "id": 138,
    "title": "Closing & Photo Session",
    "description": ""
  },
  "136": {
    "id": 136,
    "title": "GDG DevFest Kuala Lumpur 2016 Opening",
    "description": "Official start of the conference. Greetings from the organizers.",
    "speakers": [
      "nazlina"
    ],
    "tags": [
      "General"
    ]
  },
  "133": {
    "id": 133,
    "title": "Lunch",
    "description": "Foooooooood!"
  },
  "132": {
    "id": 132,
    "title": "Registration & morning Coffee",
    "description": "Get your badge, coffee, enjoy talking with tech edicts around"
  },
  "201": {
    "id": 201,
    "title": "Material Design for Success",
    "description": "Takuo will share the overview of Material Design and Libraries for using Material Design.",
    "speakers": [
      "takuo"
    ],
    "tags": [
      "Material Design"
    ]
  },
  "202": {
    "id": 202,
    "title": "Material Design Protips",
    "description": "",
    "speakers": [
      "taylor"
    ],
    "tags": [
      "Material Design"
    ]
  },
  "203": {
    "id": 203,
    "title": "Building a Chatbot using Google developer platforms",
    "description": "",
    "speakers": [
      "nazrul"
    ],
    "tags": [
      "AI"
    ]
  },
  "204": {
    "id": 204,
    "title": "Docker Awakens - Deploying Docker in your Infrastructure",
    "description": "Docker containers wrap a piece of software in a complete filesystem that contains everything needed to run: code, runtime, system tools, system libraries – anything that can be installed on a server. This guarantees that the software will always run the same, regardless of its environment.",
    "speakers": [
      "vick"
    ],
    "tags": [
      "Docker"
    ]
  },
  "205": {
    "id": 205,
    "title": "Continuous Deployment using Docker (with Kubernetes)",
    "description": "",
    "speakers": [
      "lianxun"
    ],
    "tags": [
      "Docker"
    ]
  },  
  "206": {
    "id": 206,
    "title": "Make The Web Great Again: What Comes Next for the Web",
    "description": "Henry will share the next visionary steps for the web, with Progressive Web Apps, Accelerated Mobile Pages, Physical Web, WebVR and more.",
    "speakers": [
      "henrylim"
    ],
    "tags": [
      "Web",
      "Progressive Web Apps"
    ]
  }, 
  "207": {
    "id": 207,
    "title": "Advertisement A/B Testing with Firebase ",
    "description": "In this session, Hideyoshi will show how to use Firebase Remote Config feature and utilize it to conduct A/B testing for optimizing advertisement implementations.",
    "speakers": [
      "hideyoshi"
    ],
    "tags": [
      "Firebase"
    ]
  }, 
  "301": {
    "id": 301,
    "title": "Building Android MVP using Firebase",
    "description": "Learn how to build Android MVP using Firebase with Noel.",
    "speakers": [
      "noel"
    ],
    "tags": [
      "Firebase",
      "Android"
    ]
  },    
  "302": {
    "id": 302,
    "title": "devfest:talk=@{dataBinding}",
    "description": "",
    "speakers": [
      "andhie"
    ],
    "tags": [
      "Android"
    ]
  },    
  "303": {
    "id": 303,
    "title": "Introduction to Ratpack",
    "description": "",
    "speakers": [
      "kevin"
    ],
    "tags": [
      "Android"
    ]
  },    
  "304": {
    "id": 304,
    "title": "Developers & Fintech",
    "description": "",
    "speakers": [
      "jenna"
    ],
    "tags": [
      "Community"
    ]
  },    
  "305": {
    "id": 305,
    "title": "Kotlin on Android",
    "description": "",
    "speakers": [
      "faez"
    ],
    "tags": [
      "Android"
    ]
  },    
  "306": {
    "id": 306,
    "title": "What do employer look for in hiring developers",
    "description": "",
    "speakers": [
      "sam"
    ],
    "tags": [
      "Community"
    ]
  },    
  "307": {
    "id": 307,
    "title": "Develop Augmented Reality App with Tango",
    "description": "",
    "speakers": [
      "wenjiun"
    ],
    "tags": [
      "Tango"
    ]
  },
  "401": {
    "id": 401,
    "title": "Workshop - Progressive Web Apps and Firebase",
    "description": "",
    "speakers": [
      "jt"
    ],
    "tags": [
      "Progressive Web Apps",
      "Firebase"
    ]
  },
  "402": {
    "id": 402,
    "title": "Workshop - Firebase X Android",
    "description": "",
    "speakers": [
      "qamra"
    ],
    "tags": [
      "Firebase",
      "Android"
    ]
  }                            
}



